Metadata-Version: 2.4
Name: avocado-framework-plugin-spawner-remote
Version: 113.0
Summary: Remote (host) based spawner
Home-page: http://avocado-framework.github.io/
Author: Avocado Developers
Author-email: avocado-devel@redhat.com
Requires-Dist: avocado-framework==113.0
Requires-Dist: aexpect>=1.6.2
Dynamic: author
Dynamic: author-email
Dynamic: description
Dynamic: description-content-type
Dynamic: home-page
Dynamic: requires-dist
Dynamic: summary
